sec_wall_py3-1.2-py3.12-nspkg.pth
sec_wall_py3-1.2.data/scripts/sec-wall
secwall/app_context.py
secwall/cli.py
secwall/constants.py
secwall/core.py
secwall/main.py
secwall/server.py
secwall/wsse.py
sec_wall_py3-1.2.dist-info/METADATA
sec_wall_py3-1.2.dist-info/WHEEL
sec_wall_py3-1.2.dist-info/namespace_packages.txt
sec_wall_py3-1.2.dist-info/top_level.txt
sec_wall_py3-1.2.dist-info/RECORD
